catamaran/__init__.py
catamaran/ansible.py
catamaran/github.py
catamaran-0.2.8.dist-info/METADATA
catamaran-0.2.8.dist-info/WHEEL
catamaran-0.2.8.dist-info/entry_points.txt
catamaran-0.2.8.dist-info/licenses/COPYING
catamaran-0.2.8.dist-info/RECORD
